logsignal/__init__.py
logsignal/handler.py
logsignal/signal.py
logsignal/watcher.py
logsignal/notifiers/__init__.py
logsignal/notifiers/base.py
logsignal/notifiers/console.py
logsignal/rules/__init__.py
logsignal/rules/base.py
logsignal/rules/count.py
logsignal/rules/keyword.py
logsignal/rules/level.py
logsignal/rules/silence.py
logsignal/rules/spike.py
logsignal/stats/__init__.py
logsignal/stats/base.py
logsignal/stats/entropy.py
logsignal/stats/error_rate.py
logsignal/stats/zscore.py
logsignal-0.2.0.dist-info/METADATA
logsignal-0.2.0.dist-info/WHEEL
logsignal-0.2.0.dist-info/licenses/LICENSE
logsignal-0.2.0.dist-info/RECORD
