Metadata-Version: 2.4
Name: logsignal
Version: 0.2.0
Summary: Lightweight rule-based and statistical log anomaly detector for Python
Project-URL: Homepage, https://github.com/cpprhtn/logsignal
Project-URL: Repository, https://github.com/cpprhtn/logsignal
Project-URL: Issues, https://github.com/cpprhtn/logsignal/issues
Author: Junwon Lee
License: MIT License
License-File: LICENSE
Classifier: License :: OSI Approved :: MIT License
Classifier: Operating System :: OS Independent
Classifier: Programming Language :: Python :: 3
Classifier: Topic :: Security
Classifier: Topic :: Software Development :: Libraries
Classifier: Topic :: System :: Logging
Requires-Python: >=3.12
